LICENSE
MANIFEST.in
README.md
setup.py
django_editorjs_field.egg-info/PKG-INFO
django_editorjs_field.egg-info/SOURCES.txt
django_editorjs_field.egg-info/dependency_links.txt
django_editorjs_field.egg-info/requires.txt
django_editorjs_field.egg-info/top_level.txt
editorjs_field/.DS_Store
editorjs_field/__init__.py
editorjs_field/fields.py
editorjs_field/widgets.py
editorjs_field/static/editorjs_field.css
editorjs_field/static/editorjs_field.js
editorjs_field/static/editorjs/checklist.js
editorjs_field/static/editorjs/editor.js
editorjs_field/static/editorjs/header.js
editorjs_field/templates/editorjs_widget.tpl