Metadata-Version: 2.1
Name: django-editorjs-field
Version: 0.0.3
Summary: editorjs.io integration as django model/form field
Home-page: https://github.com/ochrstn/django-editorjs-field
Author: Oliver Christen
Author-email: christen@app-logik.de
License: UNKNOWN
Platform: UNKNOWN
Classifier: Development Status :: 2 - Pre-Alpha
Classifier: Programming Language :: Python :: 3
Classifier: Framework :: Django :: 2.2
Classifier: Environment :: Web Environment
Classifier: License :: OSI Approved :: Apache Software License
Classifier: Operating System :: OS Independent
